{"map_size": [5, 10, 5, 10], "view_size": [5, 5], "entropy_regularisation_strength": 0.01, "gamma": 0.99, "max_global_steps": 80000000, "debugging_folder": "mt_task_env_5to10_ttm", "num_envs": 32, "full_view": false, "critic_coef": 0.5, "loss_scaling": 1.0, "finish_action": false, "lr_annealing_steps": 80000000, "fail_reward": -0.8, "e": 1e-05, "game": "taxi_multi_task", "arch": "mt_task_env", "termination_model_coef": 1.0, "warmup": 0, "rollout_steps": 20, "num_workers": 8, "clip_norm_type": "global", "device": "cuda", "clip_norm": 0.5, "initial_lr": 0.0007, "term_weights": [0.4, 1.6], "random_seed": 3, "verbose": 1}